<?xml version="1.0" encoding="gb2312"?>
<root>
<column id="60" name="环境保护厅" path="10954/gpimsg1/" level="1" gpi="101"><column id="91" name="组织机构简介" path="10954/gpimsg1/" level="2" gpi="91">
<column id="94" name="01C政府组成部门" path="10954/gpimsg1/" level="3" gpi="94">
<column id="2486" name="概况信息" path="10954/gpimsg1/" level="4" gpi="2486">
<column id="3665" name="机构职能" path="10954/gpimsg1/" level="5" gpi="3665">
</column>
<column id="3796" name="领导简介及分工" path="10954/gpimsg1/" level="5" gpi="3796">
</column>
<column id="3927" name="内设机构" path="10954/gpimsg1/" level="5" gpi="3927">
</column>
<column id="4058" name="直属机构" path="10954/gpimsg1/" level="5" gpi="4058">
</column>
<column id="4189" name="其他" path="10954/gpimsg1/" level="5" gpi="4189">
</column>
</column>
</column>
</column>
<column id="131" name="城乡建设、环境保护" path="10954/gpimsg1/" level="2" gpi="131">
<column id="2437" name="10C环境监测、保护与治理" path="10954/gpimsg1/" level="3" gpi="2437">
<column id="2699" name="政府文件" path="10954/gpimsg1/" level="4" gpi="2699">
<column id="4664" name="公告" path="10954/gpimsg1/" level="5" gpi="4664">
</column>
<column id="5057" name="通告" path="10954/gpimsg1/" level="5" gpi="5057">
</column>
<column id="5188" name="通知" path="10954/gpimsg1/" level="5" gpi="5188">
</column>
<column id="5581" name="报告" path="10954/gpimsg1/" level="5" gpi="5581">
</column>
<column id="5712" name="请示" path="10954/gpimsg1/" level="5" gpi="5712">
</column>
<column id="5843" name="批复" path="10954/gpimsg1/" level="5" gpi="5843">
</column>
<column id="5974" name="意见" path="10954/gpimsg1/" level="5" gpi="5974">
</column>
<column id="6105" name="函" path="10954/gpimsg1/" level="5" gpi="6105">
</column>
<column id="6236" name="会议纪要" path="10954/gpimsg1/" level="5" gpi="6236">
</column>
<column id="6367" name="其他" path="10954/gpimsg1/" level="5" gpi="6367">
</column>
</column>
<column id="2830" name="动态信息" path="10954/gpimsg1/" level="4" gpi="2830">
<column id="6498" name="工作动态" path="10954/gpimsg1/" level="5" gpi="6498">
</column>
<column id="6629" name="重要会议" path="10954/gpimsg1/" level="5" gpi="6629">
</column>
<column id="6760" name="执法监督" path="10954/gpimsg1/" level="5" gpi="6760">
</column>
<column id="6891" name="统计数据" path="10954/gpimsg1/" level="5" gpi="6891">
</column>
<column id="7022" name="公示公告" path="10954/gpimsg1/" level="5" gpi="7022">
</column>
<column id="7284" name="其他" path="10954/gpimsg1/" level="5" gpi="7284">
</column>
</column>
<column id="2961" name="突发公共事件" path="10954/gpimsg1/" level="4" gpi="2961">
<column id="7415" name="应急预案" path="10954/gpimsg1/" level="5" gpi="7415">
</column>
<column id="7546" name="应急预警" path="10954/gpimsg1/" level="5" gpi="7546">
</column>
<column id="7677" name="应对情况" path="10954/gpimsg1/" level="5" gpi="7677">
</column>
<column id="7808" name="其他" path="10954/gpimsg1/" level="5" gpi="7808">
</column>
</column>
<column id="3092" name="财政信息" path="10954/gpimsg1/" level="4" gpi="3092">
<column id="7939" name="财政预算决算" path="10954/gpimsg1/" level="5" gpi="7939">
</column>
<column id="8201" name="政府采购与招投标" path="10954/gpimsg1/" level="5" gpi="8201">
</column>
<column id="8332" name="其他" path="10954/gpimsg1/" level="5" gpi="8332">
</column>
</column>
<column id="3223" name="重大项目" path="10954/gpimsg1/" level="4" gpi="3223">
<column id="8463" name="项目审批及实施情况" path="10954/gpimsg1/" level="5" gpi="8463">
</column>
<column id="8594" name="其他" path="10954/gpimsg1/" level="5" gpi="8594">
</column>
</column>
<column id="3354" name="行政权力" path="10954/gpimsg1/" level="4" gpi="3354">
<column id="8725" name="办事指南" path="10954/gpimsg1/" level="5" gpi="8725">
</column>
<column id="8856" name="行政事业性收费" path="10954/gpimsg1/" level="5" gpi="8856">
</column>
<column id="8987" name="办理情况" path="10954/gpimsg1/" level="5" gpi="8987">
</column>
<column id="9118" name="其他" path="10954/gpimsg1/" level="5" gpi="9118">
</column>
</column>
<column id="3616" name="其他" path="10954/gpimsg1/" level="4" gpi="3616">
</column>
</column>
</column>
</column>
</root>
